brollm/__init__.py
brollm/base.py
brollm/bedrock.py
brollm/ollama.py
brollm-0.1.2.dist-info/licenses/LICENSE
brollm-0.1.2.dist-info/METADATA
brollm-0.1.2.dist-info/WHEEL
brollm-0.1.2.dist-info/top_level.txt
brollm-0.1.2.dist-info/RECORD
