Metadata-Version: 2.4
Name: brollm
Version: 0.1.2
Summary: When you think about light weight LLMs, call brollm!
Requires-Python: >=3.11
License-File: LICENSE
Requires-Dist: boto3>=1.39.17
Requires-Dist: httpx>=0.28.1
Requires-Dist: requests>=2.32.4
Dynamic: license-file
